MANIFEST.in
README.md
setup.cfg
setup.py
cytorch/__init__.py
cytorch/_version.py
cytorch/utils.py
cytorch.egg-info/PKG-INFO
cytorch.egg-info/SOURCES.txt
cytorch.egg-info/dependency_links.txt
cytorch.egg-info/top_level.txt
tests/__init__.py
tests/cytorch_test.py