Metadata-Version: 2.1
Name: cytorch
Version: 0.0.1
Summary: PyTorch in Cython
Home-page: https://learnables.github.com/cytorch
Author: Seb Arnold
Author-email: smr.arnold@gmail.com
License: License :: OSI Approved :: Apache Software License
Download-URL: https://github.com/seba-1511/cytorch/archive/0.0.1.zip
Platform: UNKNOWN
